LICENSE
MANIFEST.in
README.rst
setup.py
route53/__init__.py
route53/change_set.py
route53/connection.py
route53/exceptions.py
route53/hosted_zone.py
route53/resource_record_set.py
route53/transport.py
route53/util.py
route53.egg-info/PKG-INFO
route53.egg-info/SOURCES.txt
route53.egg-info/dependency_links.txt
route53.egg-info/requires.txt
route53.egg-info/top_level.txt
route53/xml_generators/__init__.py
route53/xml_generators/change_resource_record_set.py
route53/xml_generators/created_hosted_zone.py
route53/xml_parsers/__init__.py
route53/xml_parsers/common_change_info.py
route53/xml_parsers/common_hosted_zone.py
route53/xml_parsers/created_hosted_zone.py
route53/xml_parsers/delete_hosted_zone_by_id.py
route53/xml_parsers/get_hosted_zone_by_id.py
route53/xml_parsers/list_hosted_zones.py
route53/xml_parsers/list_resource_record_sets_by_zone_id.py