Metadata-Version: 1.1
Name: route53
Version: 1.0.1
Summary: A simple Route53 API for Python 2.7/3.x, powered by requests.
Home-page: https://github.com/gtaylor/python-route53
Author: Gregory Taylor
Author-email: gtaylor@gc-taylor.com
License: BSD
Platform: any
Classifier: Development Status :: 5 - Production/Stable
Classifier: Intended Audience :: Developers
Classifier: License :: OSI Approved :: BSD License
Classifier: Operating System :: OS Independent
Classifier: Programming Language :: Python :: 2.7
Classifier: Programming Language :: Python :: 3
Classifier: Topic :: Software Development :: Libraries :: Python Modules
